phart/__init__.py
phart/charset.py
phart/cli.py
phart/layout.py
phart/renderer.py
phart/styles.py
phart-1.1.4.dist-info/METADATA
phart-1.1.4.dist-info/WHEEL
phart-1.1.4.dist-info/entry_points.txt
phart-1.1.4.dist-info/licenses/LICENSE
phart-1.1.4.dist-info/RECORD
