Metadata-Version: 2.3
Name: phart
Version: 1.1.4
Summary: Python Hierarchical ASCII Representation Tool - Pure Python graph visualization in ASCII, no external dependencies* (*except NetworkX)
Project-URL: Homepage, https://github.com/scottvr/phart
Project-URL: Repository, https://github.com/scottvr/phart.git
Project-URL: Issues, https://github.com/scottvr/phart/issues
Author-email: Scott VR <scottvr@gmail.com>
License: MIT
Classifier: Development Status :: 5 - Production/Stable
Classifier: Intended Audience :: Developers
Classifier: License :: OSI Approved :: MIT License
Classifier: Programming Language :: Python :: 3
Classifier: Programming Language :: Python :: 3.10
Classifier: Programming Language :: Python :: 3.11
Classifier: Topic :: Software Development :: Libraries :: Python Modules
Classifier: Topic :: Text Processing :: Markup
Requires-Python: >=3.10
Requires-Dist: networkx>=3.3
Provides-Extra: default
Provides-Extra: developer
Requires-Dist: isort; extra == 'developer'
Requires-Dist: mypy>=1.1; extra == 'developer'
Requires-Dist: pre-commit>=3.2; extra == 'developer'
Provides-Extra: doc
Provides-Extra: example
Requires-Dist: pydot>=3.0.1; extra == 'example'
Provides-Extra: extra
Requires-Dist: pygraphviz>=1.14; extra == 'extra'
Provides-Extra: test
Requires-Dist: pydot; extra == 'test'
Requires-Dist: pytest-cov>=4.0; extra == 'test'
Requires-Dist: pytest>=7.2; extra == 'test'
